[
    {
        "content": "4\u00a0weeks",
        "description": "No description provided",
        "title": "-- Laboratory GitLab frontend.",
        "url": "http://74shkqokqmf5qa2oilk22z775oubpjpnlc3lsgm3xnzs2kops3bld7yd.onion"
    },
    {
        "content": "4\u00a0weeks",
        "description": "No description provided",
        "title": "",
        "url": "http://i3xi5qxvbrngh3g6o7czwjfxwjzigook7zxzjmgwg5b7xnjcn5hzciad.onion"
    },
    {
        "content": "3\u00a0weeks, 6\u00a0days",
        "description": "Today I am happy to announce the release of edge-lambda-url-authorizer 0.1.0 (ready for actual use)",
        "title": "0.1.0 edge-lambda-url-authorizer is now ready for use",
        "url": "http://ramsayswljlwqo7yvw3ovxhyzavllyduxkgh4rbobzkc263jyro6cjyd.onion"
    },
    {
        "content": "1\u00a0month, 3\u00a0weeks",
        "description": "No description provided",
        "title": "03",
        "url": "http://xfdug5vmfi6oh42fp6ahhrqdjcf7ysqat6fkp5dhvde4d7vlkqixrsad.onion"
    },
    {
        "content": "1\u00a0month, 3\u00a0weeks",
        "description": "No description provided",
        "title": "04",
        "url": "http://xfdug5vmfi6oh42fp6ahhrqdjcf7ysqat6fkp5dhvde4d7vlkqixrsad.onion"
    },
    {
        "content": "1\u00a0month, 3\u00a0weeks",
        "description": "No description provided",
        "title": "06",
        "url": "http://xfdug5vmfi6oh42fp6ahhrqdjcf7ysqat6fkp5dhvde4d7vlkqixrsad.onion"
    },
    {
        "content": "3\u00a0weeks, 5\u00a0days",
        "description": "No description provided",
        "title": "0Day Forums - Domain discussion",
        "url": "http://zerodayhuksdcephkm4zoebtqryynldg4jmhl4vwi4yakd7mrlydrsid.onion"
    },
    {
        "content": "1\u00a0month, 3\u00a0weeks",
        "description": "\u270c\ufe0f\u270c\ufe0f Jelajahi Internet lebih cepat, lebih privat.",
        "title": "1.1.1.1 \u2014 Internet Tercepat, Penyelesai DNS yang Mengutamakan Privasi",
        "url": "http://dns4torpnlfs2ifuz2s2yf3fc7rdmsbhm6rw75euj35pac6ap25zgqad.onion"
    },
    {
        "content": "1\u00a0month, 3\u00a0weeks",
        "description": "\u270c\ufe0f\u270c\ufe0f Browse a faster, more private internet.",
        "title": "1.1.1.1 \u2014 the Internet\u2019s Fastest, Privacy-First DNS Resolver",
        "url": "http://dns4torpnlfs2ifuz2s2yf3fc7rdmsbhm6rw75euj35pac6ap25zgqad.onion"
    },
    {
        "content": "1\u00a0month, 3\u00a0weeks",
        "description": "No description provided",
        "title": "11",
        "url": "http://xfdug5vmfi6oh42fp6ahhrqdjcf7ysqat6fkp5dhvde4d7vlkqixrsad.onion"
    },
    {
        "content": "4\u00a0weeks",
        "description": "No description provided",
        "title": "347-domain-separation - Tor design proposals",
        "url": "http://i3xi5qxvbrngh3g6o7czwjfxwjzigook7zxzjmgwg5b7xnjcn5hzciad.onion"
    },
    {
        "content": "4\u00a0weeks",
        "description": "No description provided",
        "title": "About - rimgo",
        "url": "http://eertpnpliglunzserhwbr2unvyfa4dj7j3iq43sktlytvhcmgj4io6id.onion"
    },
    {
        "content": "3\u00a0weeks, 5\u00a0days",
        "description": "The I2P Gitlab",
        "title": "Access and permissions \u00b7 Group \u00b7 User \u00b7 Help \u00b7 GitLab",
        "url": "http://47ggr2fijsircl3fetu64k5euw37yavfrezhag5o2imqy6vd62j6ucyd.onion"
    },
    {
        "content": "2\u00a0weeks, 5\u00a0days",
        "description": "No description provided",
        "title": "active \u2013 U.S Intelligence Community 2.0",
        "url": "http://ddanatozv47wxowehimwkzukppplz3xmko2p7eeifle6gnbmdcqsqyad.onion"
    },
    {
        "content": "4\u00a0weeks",
        "description": "No description provided",
        "title": "Add a BIP which resolves human readable names into payment info",
        "url": "http://e3y5vky4v7snefqyhbn6kcmyl5fo4cnk3a2irh2ttvwua46ww5ubl6qd.onion"
    },
    {
        "content": "3\u00a0weeks, 6\u00a0days",
        "description": "This entry will show you, how to configure onion domain for your website. This will allow access to your website through the Tor protocol, using .onion domain. Facebook did something similar. I decide",
        "title": "Add Onion domain to your website",
        "url": "http://reycdxyc24gf7jrnwutzdn3smmweizedy7uojsa7ols6sflwu25ijoyd.onion"
    },
    {
        "content": "4\u00a0weeks",
        "description": "No description provided",
        "title": "adds new article for local authoritative DNS - website_md - Source for www.anthes.is",
        "url": "http://jentyxddh2rf47gd3e43kuebyn2xsv6h72gzh46oe4rxyovvm7xe5ead.onion"
    },
    {
        "content": "3\u00a0weeks, 6\u00a0days",
        "description": "No description provided",
        "title": "All public logs - The Hidden Wiki",
        "url": "http://rk56xqf2fwp76cl4cwbarmsnn5nveqrurmvn7ek2yeqez52nq7awb2qd.onion"
    },
    {
        "content": "1\u00a0week, 4\u00a0days",
        "description": "No description provided",
        "title": "Alt Address",
        "url": "http://tp7mtouwvggdlm73vimqkuq7727a4ebrv4vf4cnk6lfg4fatxa6p2ryd.onion"
    },
    {
        "content": "4\u00a0weeks",
        "description": "No description provided",
        "title": "anonymity Archives - BusKill",
        "url": "http://www.buskillvampfih2iucxhit3qp36i2zzql3u6pmkeafvlxs3tlmot5yad.onion"
    },
    {
        "content": "1\u00a0week, 4\u00a0days",
        "description": "No description provided",
        "title": "Anonymity Management",
        "url": "http://nihilhfjmj55gfbleupwl2ub7lvbhq4kkoioatiopahfqwkcnglsawyd.onion"
    },
    {
        "content": "3\u00a0weeks, 6\u00a0days",
        "description": "SXDork is a powerful tool that utilizes the technique of google dorking to search for specific information on the internet. Google dorking is a method of",
        "title": "A Powerful Tool That Utilizes The Technique Of Google Dorking To Search For Specific Information On",
        "url": "http://u7pw75fv5lpll4adet6h6g32yayisfdcvmf5rjgb52glfysnci5gg6yd.onion"
    },
    {
        "content": "4\u00a0weeks",
        "description": "No description provided",
        "title": "A Privacy Focused DNS Setup - cwoellner.com ~ personal website & blog",
        "url": "http://cwoellfbmoo4fwpewmtwoy3nrf2rqm7aujnupj3tsawabu4m66sybead.onion"
    },
    {
        "content": "3\u00a0weeks, 6\u00a0days",
        "description": "No description provided",
        "title": "Attilas Domains und die DENIC - Anonleaks",
        "url": "http://oezronzbtheydpio2x64wzf2np6go2abdrtgprmgxh6xi6mjnha6lxad.onion"
    },
    {
        "content": "4\u00a0weeks",
        "description": "Cie\u013eom n\u00e1\u0161ho Biblick\u00e9ho API je poskytn\u00fa\u0165 preklady Biblie tak otvoren\u00e9 a pr\u00edstupn\u00e9 ako je len mo\u017en\u00e9. Pou\u017e\u00edvajte ho vo va\u0161\u00edch projektoch, webov\u00fdch aplik\u00e1ci\u00e1ch, mobiln\u00fdch aplik\u00e1ci\u00e1ch a po\u010d\u00edta\u010dov\u00fdch programoch. Nie je tu \u017eiadne obmedzenie na pou\u017e\u00edvanie, jedine biblick\u00fd text ponechajte nezmenen\u00fd.",
        "title": "Bible4u - necenz\u00farovan\u00e1 Biblia pre Darknet \u203a Api",
        "url": "http://bible4u2sleotwdzynikpusn2fkwofod3thyanfeepzh6eq7kocpdzid.onion"
    },
    {
        "content": "1\u00a0week, 4\u00a0days",
        "description": "The goal of our Bible API is to provide Bible translations as open and as accessible as possible. Feel free to use this API in your projects, web applications, mobile and desktop applications. There is no limitation as long as the biblical content remains unchanged.",
        "title": "Bible4u - uncensored Bible for Darknet \u203a Api",
        "url": "http://bible4u2lvhacg4b3to2e2veqpwmrc2c3tjf2wuuqiz332vlwmr4xbad.onion"
    },
    {
        "content": "1\u00a0week, 1\u00a0day",
        "description": "No description provided",
        "title": "BidenCash",
        "url": "http://biden3veilozweo2xubiusixn4kbfbbih23s6xsd35bzsuaz2weiz4yd.onion"
    },
    {
        "content": "1\u00a0week, 4\u00a0days",
        "description": "No description provided",
        "title": "bind9 DNS setup",
        "url": "http://nihilhfjmj55gfbleupwl2ub7lvbhq4kkoioatiopahfqwkcnglsawyd.onion"
    },
    {
        "content": "4\u00a0weeks",
        "description": "No description provided",
        "title": "BLACK MARKET \u2013 hacking Services, Drugs, Western Union Transfer, PayPal Account, Credit Cards CCV",
        "url": "http://black37fsrox4nr3r4oorwnnvrobfjfih5sbcqf6khzkcxlrhfsex4id.onion"
    },
    {
        "content": "4\u00a0weeks",
        "description": "No description provided",
        "title": "Blocking-resistant communication through domain fronting",
        "url": "http://7fa6xlti5joarlmkuhjaifa47ukgcwz6tfndgax45ocyn4rixm632jid.onion"
    },
    {
        "content": "4\u00a0weeks",
        "description": "Blog posts in category: 'Domain Names'",
        "title": "Blog",
        "url": "http://jamie3vkiwibfiwucd6vxijskbhpjdyajmzeor4mc4i7yopvpo4p7cyd.onion"
    },
    {
        "content": "4\u00a0weeks",
        "description": "Today we're pleased to formally announce a new partnership with Bonfida, the creators of Solana Name Service (SNS), to enable native resolution of SNS names in the Brave browser and Wallet.",
        "title": "Brave partners with Bonfida to offer Solana Name Service domain resolution in the Brave browser and",
        "url": "http://brave4u7jddbv7cyviptqjc7jusxh72uik7zt6adtckl5f4nwy2v72qd.onion"
    },
    {
        "content": "3\u00a0weeks, 6\u00a0days",
        "description": "You should now have a basic understanding of how the internet works. Specifically, you learned what happens when you enter a website into your browser\u2019s",
        "title": "Bug Bounty basic Part One - Blackhat Pakistan",
        "url": "http://rs2rasa34qbpslnzr5ndsmhoazugvqciq7tf7xydlwbwvz63vjtgmcyd.onion"
    },
    {
        "content": "4\u00a0weeks",
        "description": "No description provided",
        "title": "Bug Smash, Advocacy, What We're Reading,  Events",
        "url": "http://a4ygisnerpgtc5ayerl22pll6cls3oyj54qgpm7qrmb66xrxts6y3lyd.onion"
    },
    {
        "content": "4\u00a0weeks",
        "description": "No description provided",
        "title": "Build your own shrine",
        "url": "http://iaodjhoxp2eeswrqxkwc7qcocwoyqwzt2buxswpdzmnbiz7clyacrfyd.onion"
    },
    {
        "content": "4\u00a0weeks",
        "description": "No description provided",
        "title": "buy dark web hosting - Anonymous Carding shop cc \u00bb Carding shop the Verified CVV shop",
        "url": "http://blackf7ifehflns4bpg7ufnshfwffrvab5xzzxh2ubzr7mdwns3uuhid.onion"
    },
    {
        "content": "4\u00a0weeks",
        "description": "No description provided",
        "title": "buy dark web hosting - BLACK MARKET - hacking Services, Drugs, Western Union Transfer, PayPal Accoun",
        "url": "http://blackypezbmbgvmml4vllavvdvjjh6dkuth7ngnj2qx3x56xl6eaq7qd.onion"
    },
    {
        "content": "4\u00a0weeks",
        "description": "No description provided",
        "title": "buy dark web hosting \u2013 BLACK MARKET \u2013 hacking Services, Drugs, Western Union Transfer, PayPal Accoun",
        "url": "http://black37fsrox4nr3r4oorwnnvrobfjfih5sbcqf6khzkcxlrhfsex4id.onion"
    },
    {
        "content": "3\u00a0weeks, 6\u00a0days",
        "description": "BUY DARK WEB TOR .ONION DOMAIN",
        "title": "BUY DARK WEB TOR .ONION DOMAIN - Hire expert freelancers for any Dark web job, Online Millions of pe",
        "url": "http://trust3nercpefmktnhyp6hqpuz3ws3v7ynhuxynbjyaghyu72xfeafad.onion"
    },
    {
        "content": "3\u00a0weeks, 6\u00a0days",
        "description": "Some information about how domains work, choosing a registrar, and some considerations to keep in mind",
        "title": "Buying a domain name",
        "url": "http://nixnet54icmeh25qsmcsereuoareofzevjqjnw3kki6oxxey3jonwwyd.onion"
    },
    {
        "content": "1\u00a0month, 3\u00a0weeks",
        "description": "No description provided",
        "title": "buy onion domain - BUY TOR .ONION DOMAIN AND DARK WEB MARKETPLACE SCRIPTS",
        "url": "http://tordevfzeebs4nvzhpofkfywslbgmwlamonu4xfofcxzfpa4cschuiqd.onion"
    },
    {
        "content": "1\u00a0month, 2\u00a0weeks",
        "description": "No description provided",
        "title": "buy onion domain and hosting - agora road marketplace-verified vendors - secure escrow system",
        "url": "http://hacks6ho4ic4jti3mqd5b46wlavomyxz53hpkv2zfscat3u4qedbuhad.onion"
    },
    {
        "content": "4\u00a0weeks",
        "description": "No description provided",
        "title": "buy onion domain and hosting - Anonymous Carding shop cc \u00bb Carding shop the Verified CVV shop",
        "url": "http://blackf7ifehflns4bpg7ufnshfwffrvab5xzzxh2ubzr7mdwns3uuhid.onion"
    },
    {
        "content": "1\u00a0month, 4\u00a0weeks",
        "description": "No description provided",
        "title": "buy onion domain and hosting - BLACK MARKET - hacking Services, Drugs, Western Union Transfer, PayPa",
        "url": "http://bankuauydem7yibaip7qksht3hv6qv6hbl625dg5ac4pcrvbcd43tiad.onion"
    },
    {
        "content": "1\u00a0month, 2\u00a0weeks",
        "description": "No description provided",
        "title": "buy onion domain and hosting - BLACKMARKET ACTIVITIES - Buy counterfeit money online - Authenticity",
        "url": "http://faithhx5ivxbi4nippfyrn5uc6j6rlcbpjwp66caw5fgchnwutmeg6id.onion"
    },
    {
        "content": "1\u00a0month, 3\u00a0weeks",
        "description": "No description provided",
        "title": "buy onion domain and hosting - buy Bank logs and credit cards dumps shop",
        "url": "http://realggesqkpud7umjrs2ssap47dgdcbrzliewwxxnigubgapfbxhxjyd.onion"
    },
    {
        "content": "1\u00a0month, 3\u00a0weeks",
        "description": "No description provided",
        "title": "buy onion domain and hosting - Card The World Marketplace-Trust and Safety",
        "url": "http://best6kxjc5w2s4wvwqkyhmpaebdd37lpcae6is6fw6msvdhpvwerltid.onion"
    },
    {
        "content": "1\u00a0month, 3\u00a0weeks",
        "description": "No description provided",
        "title": "buy onion domain and hosting - Dark Market - guaranted secure escrow system",
        "url": "http://bankvyqmrubvkbbijv7hdowcz2brota3j25xvys642zkwn4xux7pafad.onion"
    },
    {
        "content": "1\u00a0month, 2\u00a0weeks",
        "description": "No description provided",
        "title": "buy onion domain and hosting - Darkness ll MARKET - hacking Services, Drugs, Western Union Transfer,",
        "url": "http://caretqqwrkewrwfpucsx7u3hremazk3ofeqssf4awtgekifosdorcryd.onion"
    },
    {
        "content": "4\u00a0weeks",
        "description": "No description provided",
        "title": "buy onion domain and hosting - Dark Web Anonymous Marketplace",
        "url": "http://faith4lc7za7skl327ek7iynef3kkjf3fv5oximizlrvcuugxfudzxad.onion"
    },
    {
        "content": "1\u00a0month, 3\u00a0weeks",
        "description": "No description provided",
        "title": "buy onion domain and hosting Archives - agora road marketplace-verified vendors - secure escrow syst",
        "url": "http://torsxdggg2dfh664hq73b37vxssgfxuf65utrwho2cuvgglv5zyzitqd.onion"
    },
    {
        "content": "3\u00a0weeks, 6\u00a0days",
        "description": "No description provided",
        "title": "buy onion domain and hosting Archives - BLACKMARKET ACTIVITIES- hacking Services, Drugs, Western Uni",
        "url": "http://snq232z5we4kpcyuujogjuxgebnc55eod3gfgoa5f2xuxsuwsslkfuad.onion"
    },
    {
        "content": "4\u00a0weeks",
        "description": "No description provided",
        "title": "buy onion domain and hosting Archives - Dark Tor marketplace - hacking Services, Drugs, Western Unio",
        "url": "http://fluxgw7jow7763n327dgxhow7u264j2chs3w3n73jtfy4lvqodaym2yd.onion"
    },
    {
        "content": "1\u00a0month, 4\u00a0weeks",
        "description": "No description provided",
        "title": "buy onion domain and hosting \u2013 Anonymous Marketplace",
        "url": "http://qycmqzdk2fnfqtg7rdxr72dgzi7i3c3bgoghnrswx6byoetl26oeb6yd.onion"
    },
    {
        "content": "4\u00a0weeks",
        "description": "No description provided",
        "title": "buy onion domain and hosting \u2013 BLACK MARKET \u2013 hacking Services, Drugs, Western Union Transfer, PayPa",
        "url": "http://black37fsrox4nr3r4oorwnnvrobfjfih5sbcqf6khzkcxlrhfsex4id.onion"
    },
    {
        "content": "3\u00a0weeks, 5\u00a0days",
        "description": "No description provided",
        "title": "buy onion domain and hosting \u2013 Dark Road Market",
        "url": "http://zr54hyfaacfxi5ehz3nqt65bnqwdyqnaho3p263f7ebox7zraewgutyd.onion"
    },
    {
        "content": "1\u00a0month, 2\u00a0weeks",
        "description": "No description provided",
        "title": "buy onion domain name - agora road marketplace-verified vendors - secure escrow system",
        "url": "http://hacks6ho4ic4jti3mqd5b46wlavomyxz53hpkv2zfscat3u4qedbuhad.onion"
    },
    {
        "content": "4\u00a0weeks",
        "description": "No description provided",
        "title": "buy onion domain name - Anonymous Carding shop cc \u00bb Carding shop the Verified CVV shop",
        "url": "http://blackf7ifehflns4bpg7ufnshfwffrvab5xzzxh2ubzr7mdwns3uuhid.onion"
    },
    {
        "content": "1\u00a0month, 1\u00a0week",
        "description": "No description provided",
        "title": "buy onion domain name - BLACK MARKET - hacking Services, Drugs, Western Union Transfer, PayPal Accou",
        "url": "http://onion2o2qbkbpk65kt2kfvmnysgxzkio25ick6f425lhgpgnt7rvclad.onion"
    },
    {
        "content": "1\u00a0month, 2\u00a0weeks",
        "description": "No description provided",
        "title": "buy onion domain name - BLACKMARKET ACTIVITIES - Buy counterfeit money online - Authenticity Undispu",
        "url": "http://faithhx5ivxbi4nippfyrn5uc6j6rlcbpjwp66caw5fgchnwutmeg6id.onion"
    },
    {
        "content": "1\u00a0month, 3\u00a0weeks",
        "description": "No description provided",
        "title": "buy onion domain name - buy Bank logs and credit cards dumps shop",
        "url": "http://realggesqkpud7umjrs2ssap47dgdcbrzliewwxxnigubgapfbxhxjyd.onion"
    },
    {
        "content": "1\u00a0month, 3\u00a0weeks",
        "description": "No description provided",
        "title": "buy onion domain name - Card The World Marketplace-Trust and Safety",
        "url": "http://best6kxjc5w2s4wvwqkyhmpaebdd37lpcae6is6fw6msvdhpvwerltid.onion"
    },
    {
        "content": "1\u00a0month, 3\u00a0weeks",
        "description": "No description provided",
        "title": "buy onion domain name - Dark Market - guaranted secure escrow system",
        "url": "http://bankvyqmrubvkbbijv7hdowcz2brota3j25xvys642zkwn4xux7pafad.onion"
    },
    {
        "content": "1\u00a0month, 2\u00a0weeks",
        "description": "No description provided",
        "title": "buy onion domain name - Darkness ll MARKET - hacking Services, Drugs, Western Union Transfer, PayPal",
        "url": "http://caretqqwrkewrwfpucsx7u3hremazk3ofeqssf4awtgekifosdorcryd.onion"
    },
    {
        "content": "4\u00a0weeks",
        "description": "No description provided",
        "title": "buy onion domain name - Dark Web Anonymous Marketplace",
        "url": "http://faith4lc7za7skl327ek7iynef3kkjf3fv5oximizlrvcuugxfudzxad.onion"
    },
    {
        "content": "1\u00a0month, 3\u00a0weeks",
        "description": "No description provided",
        "title": "buy onion domain name Archives - agora road marketplace-verified vendors - secure escrow system",
        "url": "http://torsxdggg2dfh664hq73b37vxssgfxuf65utrwho2cuvgglv5zyzitqd.onion"
    },
    {
        "content": "3\u00a0weeks, 6\u00a0days",
        "description": "No description provided",
        "title": "buy onion domain name Archives - BLACKMARKET ACTIVITIES- hacking Services, Drugs, Western Union Tran",
        "url": "http://snq232z5we4kpcyuujogjuxgebnc55eod3gfgoa5f2xuxsuwsslkfuad.onion"
    },
    {
        "content": "4\u00a0weeks",
        "description": "No description provided",
        "title": "buy onion domain name Archives - Dark Tor marketplace - hacking Services, Drugs, Western Union Trans",
        "url": "http://fluxgw7jow7763n327dgxhow7u264j2chs3w3n73jtfy4lvqodaym2yd.onion"
    },
    {
        "content": "4\u00a0weeks",
        "description": "No description provided",
        "title": "buy onion domain name \u2013 BLACK MARKET \u2013 hacking Services, Drugs, Western Union Transfer, PayPal Accou",
        "url": "http://black37fsrox4nr3r4oorwnnvrobfjfih5sbcqf6khzkcxlrhfsex4id.onion"
    },
    {
        "content": "3\u00a0weeks, 5\u00a0days",
        "description": "No description provided",
        "title": "buy onion domain name \u2013 Dark Road Market",
        "url": "http://spvtt7qaost62hjhvoj5gzdcpbnaav5bcxltcnmw327vndll32dspiqd.onion"
    },
    {
        "content": "3\u00a0weeks, 6\u00a0days",
        "description": "Some steps to change a domain of a Gitea instance.",
        "title": "Changing domain of a Gitea instance - Solve Computer Science",
        "url": "http://usggwz6vwth276fdyccskoba5u2jis5ugv2ew2fy2blowgf2dv73axad.onion"
    },
    {
        "content": "1\u00a0week, 4\u00a0days",
        "description": "Send large attachments using temporary email",
        "title": "Compose a new Email",
        "url": "http://csmail3thcskmzvjicww3qdkvrhb6pb5s7zjqtb3gdst6guby2stsiqd.onion"
    },
    {
        "content": "4\u00a0weeks",
        "description": "No description provided",
        "title": "Create your order",
        "url": "http://eihwm4gg64czev5ffpzhf2mau6eqxyvkrwrdo3f7beyig5pdxiy7lxid.onion"
    },
    {
        "content": "3\u00a0weeks, 6\u00a0days",
        "description": "No description provided",
        "title": "Creating Facebook - Tortoise Wiki",
        "url": "http://qezqo7c2mvdk2ml2ys626hlh7ezva75wwwoawcuc7xncp37kedumv2ad.onion"
    },
    {
        "content": "3\u00a0weeks, 6\u00a0days",
        "description": "No description provided",
        "title": "Creating Galaxy3 - Tortoise Wiki",
        "url": "http://qezqo7c2mvdk2ml2ys626hlh7ezva75wwwoawcuc7xncp37kedumv2ad.onion"
    },
    {
        "content": "3\u00a0weeks, 6\u00a0days",
        "description": "No description provided",
        "title": "Creating Nervous System - Key Wiki",
        "url": "http://qgu356nwwy7dweo276qk6rkts4pgpgm3vjjmedsifunu5yope52vdbid.onion"
    },
    {
        "content": "3\u00a0weeks, 6\u00a0days",
        "description": "No description provided",
        "title": "Creating Protonmail - Tortoise Wiki",
        "url": "http://qezqo7c2mvdk2ml2ys626hlh7ezva75wwwoawcuc7xncp37kedumv2ad.onion"
    },
    {
        "content": "3\u00a0weeks, 6\u00a0days",
        "description": "No description provided",
        "title": "Creating TorGuerrillaMail - Tortoise Wiki",
        "url": "http://qezqo7c2mvdk2ml2ys626hlh7ezva75wwwoawcuc7xncp37kedumv2ad.onion"
    },
    {
        "content": "1\u00a0week, 4\u00a0days",
        "description": "Terms of Service",
        "title": "cs.email Terms of Service",
        "url": "http://csmail3thcskmzvjicww3qdkvrhb6pb5s7zjqtb3gdst6guby2stsiqd.onion"
    },
    {
        "content": "2\u00a0weeks, 5\u00a0days",
        "description": "No description provided",
        "title": "currently \u2013 U.S Intelligence Community 2.0",
        "url": "http://ddanatozv47wxowehimwkzukppplz3xmko2p7eeifle6gnbmdcqsqyad.onion"
    },
    {
        "content": "1\u00a0month, 3\u00a0weeks",
        "description": "No description provided",
        "title": "custom domain - BUY TOR .ONION DOMAIN AND DARK WEB MARKETPLACE SCRIPTS",
        "url": "http://tordevfzeebs4nvzhpofkfywslbgmwlamonu4xfofcxzfpa4cschuiqd.onion"
    },
    {
        "content": "3\u00a0weeks, 6\u00a0days",
        "description": "No description provided",
        "title": "custom domain - Hire expert freelancers for any Dark web job, Online Millions of people use darkweb",
        "url": "http://trust3nercpefmktnhyp6hqpuz3ws3v7ynhuxynbjyaghyu72xfeafad.onion"
    },
    {
        "content": "2\u00a0weeks, 5\u00a0days",
        "description": "No description provided",
        "title": "Cyber Jihad Domain \u2013 Dancho Danchev's Leading Cyber Threat Intelligence Products Portal",
        "url": "http://ddaneq556vp3dyjfsjobztoe3pxnm7ad3curft64sbmpqw3mknjiw4yd.onion"
    },
    {
        "content": "1\u00a0week, 1\u00a0day",
        "description": "No description provided",
        "title": "CyberSec101x Domain - Highly Secure ProtonMail E-mail Account - 3 High Speed VPN Connections 1 Year",
        "url": "http://darkdwabcvtz65reu5lzeb5i2tbzgmctjya73cxcyotwacazhsas76id.onion"
    },
    {
        "content": "1\u00a0month, 1\u00a0week",
        "description": "Escrow: Auto-Finalized in 2 DaysInstant Delivery (Digital)",
        "title": "CyberSec101x Domain \u2013 Highly Secure ProtonMail E-mail Account \u2013 3 High Speed VPN Connections 1 Year",
        "url": "http://nwvkath3wtjvqazhhl6gcktkokvzmgjwb6le42koj7zan6faxbugm7ad.onion"
    },
    {
        "content": "4\u00a0weeks",
        "description": "No description provided",
        "title": "Daniel's Hosting - FAQ",
        "url": "http://bxuldv5kaynguiq6orjmrqxpgtafv3flbgqfpbrw6gv3rzdfdhk4psyd.onion"
    },
    {
        "content": "4\u00a0weeks",
        "description": "Daniel Dark Web Hosting offers a wide range of dark web hosting services, including domain registration, shared hosting, VPS hosting",
        "title": "Daniel Hosting - Hidden Wiki",
        "url": "http://darkwebp7lyr44rpgqdtevalty2pk5oqmc6m2cnicnix7itelt3lp3id.onion"
    },
    {
        "content": "3\u00a0weeks, 6\u00a0days",
        "description": "No description provided",
        "title": "Daniel Hosting \u2013 Hidden Wiki",
        "url": "http://oq2h5qzmhyu4arveocoa2m2h3musxqjr7x3lo7xm2v4f6xg77vzeu5yd.onion"
    },
    {
        "content": "3\u00a0weeks, 6\u00a0days",
        "description": "No description provided",
        "title": "Dark Leak Market",
        "url": "http://darklmmmfuonklpy6s3tmvk5mrcdi7iapaw6eka45esmoryiiuug6aid.onion"
    },
    {
        "content": "4\u00a0weeks",
        "description": "No description provided",
        "title": "Dark Market \u2013 guaranted secure escrow system",
        "url": "http://faithwdm4f6up2wrbuowz4fipytqu2rdzs5cin3lwjlpifzzfvzda5id.onion"
    },
    {
        "content": "3\u00a0weeks, 6\u00a0days",
        "description": "Darknet Horizon network, the engine search link legal .onion",
        "title": "Darknet Horizon Network",
        "url": "http://nbvri7hbptgyqvzxhskvxjq7olokkmhsqzhjikfzk2hm5slafuu36did.onion"
    },
    {
        "content": "1\u00a0month, 3\u00a0weeks",
        "description": "No description provided",
        "title": "dark web domain - BUY TOR .ONION DOMAIN AND DARK WEB MARKETPLACE SCRIPTS",
        "url": "http://tordevfzeebs4nvzhpofkfywslbgmwlamonu4xfofcxzfpa4cschuiqd.onion"
    },
    {
        "content": "3\u00a0weeks, 6\u00a0days",
        "description": "No description provided",
        "title": "dark web domain - Hire expert freelancers for any Dark web job, Online Millions of people use darkwe",
        "url": "http://trust3nercpefmktnhyp6hqpuz3ws3v7ynhuxynbjyaghyu72xfeafad.onion"
    },
    {
        "content": "4\u00a0weeks",
        "description": "Anonymous Web Hosting. Dark Web Hosting. Run Your Tor Services Completely Anonymouos.  We will host any type of web site absolutely no limits!",
        "title": "Dark Web Hosting",
        "url": "http://jqemut36mptfmrukegaztcu7yshqvvckrxkh4nl3lplre6nupbysewyd.onion"
    },
    {
        "content": "4\u00a0weeks",
        "description": "Two days after the American far right\u2019s failed fascist coup on January 6th, 2021 that left five people dead in Washington, DC, Twitter (finally) permanently banned the would-be dictator responsible for inciting the mob from their platform. Shortly thereafter, the social media network most closely a\u2026",
        "title": "Deplatforming Parler will have consequences for which we must immediately prepare \u2014 Tech Learning Co",
        "url": "http://lpiyu33yusoalp5kh3f4hak2so2sjjvjw5ykyvu2dulzosgvuffq6sad.onion"
    },
    {
        "content": "1\u00a0month, 3\u00a0weeks",
        "description": "No description provided",
        "title": "Disabling mail sending from your domain",
        "url": "http://xfdug5vmfi6oh42fp6ahhrqdjcf7ysqat6fkp5dhvde4d7vlkqixrsad.onion"
    },
    {
        "content": "4\u00a0weeks",
        "description": "Disroot is a platform providing online services based on principles of freedom, privacy, federation and decentralization.",
        "title": "DisNews #3 - Lacre progress; Custom domain linking; New dashboard; Muppeth's quitting; 3rd volunteer",
        "url": "http://j4dhkkxfcsvzvh3p5djkmuehhgd6t6l7wmzih6b4ss744hegwkiae7ad.onion"
    },
    {
        "content": "3\u00a0weeks, 6\u00a0days",
        "description": "Protecting yourself from malicious third parties leveraging DNS and root certificates",
        "title": "DNS and Root Certificates",
        "url": "http://nixnet54icmeh25qsmcsereuoareofzevjqjnw3kki6oxxey3jonwwyd.onion"
    },
    {
        "content": "4\u00a0weeks",
        "description": "No description provided",
        "title": "dns Archives - BusKill",
        "url": "http://www.buskillvampfih2iucxhit3qp36i2zzql3u6pmkeafvlxs3tlmot5yad.onion"
    },
    {
        "content": "3\u00a0weeks, 6\u00a0days",
        "description": "No description provided",
        "title": "Dns attacks",
        "url": "http://rtdxrpt3wx3sk7mkp2l2ku7mrvrrgzzpvff7ik76ggss6by434fd6vid.onion"
    },
    {
        "content": "4\u00a0weeks",
        "description": "No description provided",
        "title": "Dns poisoning",
        "url": "http://dgquftlj2h3rhbalvz6o6s7ilg32bg763eqjyb76wlv4w2cndfzzrdid.onion"
    },
    {
        "content": "3\u00a0weeks, 6\u00a0days",
        "description": "Domain - LuCYcl",
        "title": "Domain - LuCYcl",
        "url": "http://pjnd7r7qiuntnwvzlv374etbuyi7a7qyges7r2i3m2iy7lajmlytlhqd.onion"
    },
    {
        "content": "3\u00a0weeks, 6\u00a0days",
        "description": "Online journal about autism, computing, economics, environmentalism, philosophy, privacy, society, and spirituality.",
        "title": "Domain Change Announcement",
        "url": "http://nick6gsepvtmkcpibpid6dqtqroxt62u6ab4ep65vxrenffruumj6jad.onion"
    },
    {
        "content": "4\u00a0weeks",
        "description": "No description provided",
        "title": "Domain Fronting, Relay Help, User Needs, New Interns, Events",
        "url": "http://a4ygisnerpgtc5ayerl22pll6cls3oyj54qgpm7qrmb66xrxts6y3lyd.onion"
    },
    {
        "content": "4\u00a0weeks",
        "description": "No description provided",
        "title": "Domain name meanings \u2014 anthesis",
        "url": "http://jentyxddh2rf47gd3e43kuebyn2xsv6h72gzh46oe4rxyovvm7xe5ead.onion"
    },
    {
        "content": "1\u00a0month, 3\u00a0weeks",
        "description": "Domain parser for IPAddress.com Reverse IP Lookup. Writen in Python 3.",
        "title": "Domain Parser For IPAddress.com Reverse IP Lookup - #1 Mobile Hacker For Hire",
        "url": "http://dreamshk3pkeizw2rfdxn73odxuido3rwevvt4sfl3ewc4frvcf5h4yd.onion"
    },
    {
        "content": "1\u00a0month, 4\u00a0weeks",
        "description": "No description provided",
        "title": "Domain Privacy - Knowledgebase - Mynymbox",
        "url": "http://mynymefqtjhkxg67sj5orcsu75ofhvnyk7tpuowfe4jyhfvqsfsbhzyd.onion"
    },
    {
        "content": "3\u00a0weeks, 6\u00a0days",
        "description": "No description provided",
        "title": "Domain redirects relaxed",
        "url": "http://pfcgmo5hwfffwhis3zty2u2ufryrnzypue34h74va6ykw5iazgcvvtqd.onion"
    },
    {
        "content": "1\u00a0month, 4\u00a0weeks",
        "description": "No description provided",
        "title": "Domain transfer - Knowledgebase - Mynymbox",
        "url": "http://mynymefqtjhkxg67sj5orcsu75ofhvnyk7tpuowfe4jyhfvqsfsbhzyd.onion"
    },
    {
        "content": "1\u00a0month, 3\u00a0weeks",
        "description": "0xacab",
        "title": "domain \u00b7 Topics \u00b7 GitLab",
        "url": "http://wmj5kiic7b6kjplpbvwadnht2nh2qnkbnqtcv3dyvpqtz7ssbssftxid.onion"
    },
    {
        "content": "2\u00a0weeks, 5\u00a0days",
        "description": "No description provided",
        "title": "domain \u2013 U.S Intelligence Community 2.0",
        "url": "http://ddanatozv47wxowehimwkzukppplz3xmko2p7eeifle6gnbmdcqsqyad.onion"
    },
    {
        "content": "4\u00a0weeks",
        "description": "I guess it was in early 2019 when Google announced they would be breaking thousands of development and test environments by making the \".dev\" domain a thing (archive link to announcement). Four years later they sold their entire Google Domains operation to Squarespace (archived). And, yea\u2026",
        "title": "Don't get me started on Squarespace - Marty McGuire",
        "url": "http://martymcgfuraocsgy2a25btl5srhifcdud6m4eiphz2mq6fafttwh7qd.onion"
    },
    {
        "content": "3\u00a0weeks, 6\u00a0days",
        "description": "No description provided",
        "title": "DuckDuckGo \u2014 Spyware Watchdog",
        "url": "http://spywareitdaiuyfo2sqb5vsg7mek5cjabdr73luhnda57t2hyuzg7yyd.onion"
    },
    {
        "content": "3\u00a0weeks, 6\u00a0days",
        "description": "No description provided",
        "title": "Editing Darknet web development (section) - Key Wiki",
        "url": "http://qgu356nwwy7dweo276qk6rkts4pgpgm3vjjmedsifunu5yope52vdbid.onion"
    },
    {
        "content": "4\u00a0weeks",
        "description": "Using Whonix with KVM (Kernel Virtual Machine)",
        "title": "Editing KVM (section) - Whonix",
        "url": "http://dds6qkxpeiqvogt4y2fd7vtsxq6pvokekb2h4la7jd4iwl4ljuawu5qd.onion"
    },
    {
        "content": "3\u00a0weeks, 5\u00a0days",
        "description": "No description provided",
        "title": "Editing Main Page (section) - Freedom Wiki",
        "url": "http://vavi6vaewwf7gtpsjxeufyanr7qxcfd4upcdgm2wg2xzanqzv3uahiyd.onion"
    },
    {
        "content": "3\u00a0weeks, 6\u00a0days",
        "description": "No description provided",
        "title": "Editing Main Page (section) - Key Wiki",
        "url": "http://qgu356nwwy7dweo276qk6rkts4pgpgm3vjjmedsifunu5yope52vdbid.onion"
    },
    {
        "content": "3\u00a0weeks, 6\u00a0days",
        "description": "No description provided",
        "title": "Editing Main Page (section) - Tortoise Wiki",
        "url": "http://qezqo7c2mvdk2ml2ys626hlh7ezva75wwwoawcuc7xncp37kedumv2ad.onion"
    },
    {
        "content": "3\u00a0weeks, 5\u00a0days",
        "description": "No description provided",
        "title": "Editing Neural circuit (section) - Freedom Wiki",
        "url": "http://vavi6vaewwf7gtpsjxeufyanr7qxcfd4upcdgm2wg2xzanqzv3uahiyd.onion"
    },
    {
        "content": "3\u00a0weeks, 6\u00a0days",
        "description": "No description provided",
        "title": "Editing Neural circuit (section) - Key Wiki",
        "url": "http://qgu356nwwy7dweo276qk6rkts4pgpgm3vjjmedsifunu5yope52vdbid.onion"
    },
    {
        "content": "3\u00a0weeks, 6\u00a0days",
        "description": "No description provided",
        "title": "Editing Security (section) - Key Wiki",
        "url": "http://qgu356nwwy7dweo276qk6rkts4pgpgm3vjjmedsifunu5yope52vdbid.onion"
    },
    {
        "content": "3\u00a0weeks, 5\u00a0days",
        "description": "Hidden Wiki : Find the latest en most trusted Onion links. In here you will find the best DarkNet markets , search engines , email providers",
        "title": "Elude",
        "url": "http://ze2f2gus5s2hftnyrzanmuybgjw55br7wmdp6mhzl6ntwbcp6jvrceqd.onion"
    },
    {
        "content": "4\u00a0weeks",
        "description": "No description provided",
        "title": "Email Address Hacking",
        "url": "http://jnbjuqiwug3pkxxzcdb2zfrj72jokjud2iwnfjo7fzzc3zjlsamocsyd.onion"
    },
    {
        "content": "3\u00a0weeks, 5\u00a0days",
        "description": "No description provided",
        "title": "Email Servers - riseup.net",
        "url": "http://vww6ybaluuo4gfuuf6zvlt23hvg2pcfayco5iiwhv3plo6o7bewivoid.onion"
    },
    {
        "content": "4\u00a0weeks",
        "description": "No description provided",
        "title": "email [\ud83d\udd12 Cybersecurity for lawyers]",
        "url": "http://h7isucmawckzflxhipflydxvxpaytk5fozfk5immffg66rhboc74yxyd.onion"
    },
    {
        "content": "4\u00a0weeks",
        "description": "Freedom of the Press Foundation protects and defends adversarial journalism in the 21st century.",
        "title": "Encrypting email with Mailvelope",
        "url": "http://fpfjxcrmcpdlnhwj5e6mhm2gdlr3ift35jich4zwnzy3iiueohg3sbqd.onion"
    },
    {
        "content": "4\u00a0weeks",
        "description": "No description provided",
        "title": "Example Domain",
        "url": "http://exmple27tdg5nesxaao6khfuk5ac723n7tpqkzhyytnjm2ltt6tgkhyd.onion"
    },
    {
        "content": "3\u00a0weeks, 5\u00a0days",
        "description": "No description provided",
        "title": "exitpolicy.conf",
        "url": "http://vzoc4aylgsqwexe6okjbz2ix5atgdv5xyibnkcekmtg4u23syz6a7rid.onion"
    },
    {
        "content": "2\u00a0weeks, 5\u00a0days",
        "description": "No description provided",
        "title": "Exposing A Currently Active Domain Portfolio of Cybercrime Friendly Forum Communities \u2013 Part Two \u2013 A",
        "url": "http://ddanatozv47wxowehimwkzukppplz3xmko2p7eeifle6gnbmdcqsqyad.onion"
    },
    {
        "content": "2\u00a0weeks, 5\u00a0days",
        "description": "No description provided",
        "title": "Exposing a Currently Active Rock Phish Domain Portfolio \u2013 Historical OSINT \u2013 U.S Intelligence Commun",
        "url": "http://ddanatozv47wxowehimwkzukppplz3xmko2p7eeifle6gnbmdcqsqyad.onion"
    },
    {
        "content": "4\u00a0weeks",
        "description": "Users can expose IP of Tor domains using WordPress XMLRPC ping function. This technique is used by law enforcement to track down illegal activities on the dark.",
        "title": "Exposing WordPress Tor domain IP using XMLRPC",
        "url": "http://joshua7shia5tlma33civ42uo3wjpj57q2keq33zixt5bit7auhbr2qd.onion"
    },
    {
        "content": "4\u00a0weeks",
        "description": "No description provided",
        "title": "facebook Archives - BusKill",
        "url": "http://www.buskillvampfih2iucxhit3qp36i2zzql3u6pmkeafvlxs3tlmot5yad.onion"
    },
    {
        "content": "1\u00a0month, 3\u00a0weeks",
        "description": "ExchangeFinder is a simple and open-source tool that tries to find Micrsoft Exchange instance for a given domain based on the top common DNS names for",
        "title": "Find Microsoft Exchange Instance For A Given Domain And Identify The Exact Version - #1 Mobile Hacke",
        "url": "http://dreamshk3pkeizw2rfdxn73odxuido3rwevvt4sfl3ewc4frvcf5h4yd.onion"
    },
    {
        "content": "3\u00a0weeks, 6\u00a0days",
        "description": "ExchangeFinder is a simple and open-source tool that tries to find Micrsoft Exchange instance for a given domain based on the top common DNS names for",
        "title": "Find Microsoft Exchange Instance For A Given Domain And Identify The Exact Version - #1 Y3llowl4bs H",
        "url": "http://twd6bfktlkhwluhj2ghjthx55pnp2dcuuhf6qqjz7vm2krsmwpz6crad.onion"
    },
    {
        "content": "4\u00a0weeks",
        "description": "No description provided",
        "title": "firm_website [\ud83d\udd12 Cybersecurity for lawyers]",
        "url": "http://h7isucmawckzflxhipflydxvxpaytk5fozfk5immffg66rhboc74yxyd.onion"
    },
    {
        "content": "3\u00a0weeks, 6\u00a0days",
        "description": "FlokiNET provides Secure, Stable and Anonymous Webhosting, Virtual Servers, Colocation, Dedicated Servers, DDoS Protection & more in Iceland Finland Netherlands and Romania",
        "title": "FlokiNET - Secure, Anonymous, Offshore",
        "url": "http://vf7vsrexwb7e4j65idp4hq4eqlvjiwrnvi3jnb4st7oteer5tzgvhaqd.onion"
    },
    {
        "content": "3\u00a0weeks, 5\u00a0days",
        "description": "Group for Apps and Services on Exascale Research Infrastructure is a research, development, and teaching unit at FIDIT + MedRi.",
        "title": "Fly away, little bird - GASERI",
        "url": "http://vcwkbqby652dtqgbtbtr6ouvs6fu5abx5z45dmlug6dl55d6zcadsuqd.onion"
    },
    {
        "content": "4\u00a0weeks",
        "description": "No description provided",
        "title": "free dark web hosting - Anonymous Carding shop cc \u00bb Carding shop the Verified CVV shop",
        "url": "http://blackf7ifehflns4bpg7ufnshfwffrvab5xzzxh2ubzr7mdwns3uuhid.onion"
    },
    {
        "content": "4\u00a0weeks",
        "description": "No description provided",
        "title": "free dark web hosting \u2013 BLACK MARKET \u2013 hacking Services, Drugs, Western Union Transfer, PayPal Accou",
        "url": "http://black37fsrox4nr3r4oorwnnvrobfjfih5sbcqf6khzkcxlrhfsex4id.onion"
    },
    {
        "content": "1\u00a0week, 4\u00a0days",
        "description": "No description provided",
        "title": "Free Disposable Email Addresses \u00bb Alt Address",
        "url": "http://tp7mtouwvggdlm73vimqkuq7727a4ebrv4vf4cnk6lfg4fatxa6p2ryd.onion"
    },
    {
        "content": "3\u00a0weeks, 6\u00a0days",
        "description": "No description provided",
        "title": "free domain method - Blackhat Pakistan",
        "url": "http://rs2rasa34qbpslnzr5ndsmhoazugvqciq7tf7xydlwbwvz63vjtgmcyd.onion"
    },
    {
        "content": "4\u00a0weeks",
        "description": "No description provided",
        "title": "Freedom Hosting Reloaded",
        "url": "http://4sptj2sr674frmtqgja4wobz3fmpi7ichcp7ihydcxavkcbjm3neruid.onion"
    },
    {
        "content": "4\u00a0weeks",
        "description": "The principles of Free Software are simple but it is important to not get confused by the underlying complexity caused by its long history. Learn about the...",
        "title": "Free Software - FSFE",
        "url": "http://fsfeorg3v5yaitpw5362njmkgvwm6z2qojrgol6edqyaqswlpliqrqid.onion"
    },
    {
        "content": "3\u00a0weeks, 6\u00a0days",
        "description": "Learn about our WebBox VPS packages, which can serve HTML + PHP websites out-of-the-box, and are pre-loaded with Python 3 (+ packages such as Django/Flask), NodeJS, MySQL (MariaDB), PostgreSQL and MORE.    Private, cheap, AND convenient!",
        "title": "Getting started with a Privex Debian WebBox VPS",
        "url": "http://privex3guvvasyer6pxz2fqcgy56auvw5egkir6ykwpptferdcb5toad.onion"
    },
    {
        "content": "3\u00a0weeks, 6\u00a0days",
        "description": "No description provided",
        "title": "GPUs From All Major Suppliers Are Vulnerable To New Pixel-Stealing Attack",
        "url": "http://rambleeysnwq5bpbefpycwkdvrxbhrs2e2te7prnrq4rravx7suak5qd.onion"
    },
    {
        "content": "4\u00a0weeks",
        "description": "No description provided",
        "title": "hacking domain server - Anonymous Carding shop cc \u00bb Carding shop the Verified CVV shop",
        "url": "http://blackf7ifehflns4bpg7ufnshfwffrvab5xzzxh2ubzr7mdwns3uuhid.onion"
    },
    {
        "content": "4\u00a0weeks",
        "description": "No description provided",
        "title": "hacking domain server - BLACK MARKET - hacking Services, Drugs, Western Union Transfer, PayPal Accou",
        "url": "http://blackypezbmbgvmml4vllavvdvjjh6dkuth7ngnj2qx3x56xl6eaq7qd.onion"
    },
    {
        "content": "1\u00a0month, 2\u00a0weeks",
        "description": "No description provided",
        "title": "hacking domain server - BLACKMARKET ACTIVITIES - Buy counterfeit money online - Authenticity Undispu",
        "url": "http://faithhx5ivxbi4nippfyrn5uc6j6rlcbpjwp66caw5fgchnwutmeg6id.onion"
    },
    {
        "content": "1\u00a0month, 3\u00a0weeks",
        "description": "No description provided",
        "title": "hacking domain server - buy Bank logs and credit cards dumps shop",
        "url": "http://realggesqkpud7umjrs2ssap47dgdcbrzliewwxxnigubgapfbxhxjyd.onion"
    },
    {
        "content": "1\u00a0month, 3\u00a0weeks",
        "description": "No description provided",
        "title": "hacking domain server - Card The World Marketplace-Trust and Safety",
        "url": "http://best6kxjc5w2s4wvwqkyhmpaebdd37lpcae6is6fw6msvdhpvwerltid.onion"
    },
    {
        "content": "1\u00a0month, 3\u00a0weeks",
        "description": "No description provided",
        "title": "hacking domain server - Dark Market - guaranted secure escrow system",
        "url": "http://bankvyqmrubvkbbijv7hdowcz2brota3j25xvys642zkwn4xux7pafad.onion"
    },
    {
        "content": "1\u00a0month, 2\u00a0weeks",
        "description": "No description provided",
        "title": "hacking domain server - Darkness ll MARKET - hacking Services, Drugs, Western Union Transfer, PayPal",
        "url": "http://caretqqwrkewrwfpucsx7u3hremazk3ofeqssf4awtgekifosdorcryd.onion"
    },
    {
        "content": "4\u00a0weeks",
        "description": "No description provided",
        "title": "hacking domain server - Dark Web Anonymous Marketplace",
        "url": "http://faith4lc7za7skl327ek7iynef3kkjf3fv5oximizlrvcuugxfudzxad.onion"
    },
    {
        "content": "1\u00a0month, 3\u00a0weeks",
        "description": "No description provided",
        "title": "hacking domain server Archives - agora road marketplace-verified vendors - secure escrow system",
        "url": "http://torsxdggg2dfh664hq73b37vxssgfxuf65utrwho2cuvgglv5zyzitqd.onion"
    },
    {
        "content": "3\u00a0weeks, 6\u00a0days",
        "description": "No description provided",
        "title": "hacking domain server Archives - BLACKMARKET ACTIVITIES- hacking Services, Drugs, Western Union Tran",
        "url": "http://snq232z5we4kpcyuujogjuxgebnc55eod3gfgoa5f2xuxsuwsslkfuad.onion"
    },
    {
        "content": "3\u00a0weeks, 5\u00a0days",
        "description": "No description provided",
        "title": "hacking domain server \u2013 Dark Road Market",
        "url": "http://d5mvntqvyn3qze2cpmytjrfud6zmlc5k4eafiwws4i7w5ogvuwvpadqd.onion"
    },
    {
        "content": "1\u00a0week, 4\u00a0days",
        "description": "Wikipedia is one of the most popular web resources of the open part of the Internet. On the dark web, you may come across Hidden Wiki(or The Hidden Wiki).",
        "title": "Hidden Wiki - Darknet marketplaces onion link.",
        "url": "http://zrmmwbzspq65sxd2tkgiio5hlvuzg2niuc2whpeigcbfldxdexi4hyqd.onion"
    },
    {
        "content": "4\u00a0weeks",
        "description": "No description provided",
        "title": "Hidden Wiki - Hidden Wiki",
        "url": "http://hiddenweltxdtnjylanx3x2vsdjrp7yufjxzwe7nebu7sat3a5hiloid.onion"
    },
    {
        "content": "4\u00a0weeks",
        "description": "No description provided",
        "title": "Hidden Wiki",
        "url": "http://hiddenweltxdtnjylanx3x2vsdjrp7yufjxzwe7nebu7sat3a5hiloid.onion"
    },
    {
        "content": "4\u00a0weeks",
        "description": "Looking to Hire A Hacker - dwhacker@keemail.me for blogger website, our agency is best in it. All online ethical services will be at cheap prices by white hat professionals.",
        "title": "Hire A Hacker - dwhacker@keemail.me For Blogger Website White Hat Professional",
        "url": "http://lmslpmvtbbcbiwozvsusjky557h4s3ilq3fft7x2vwgyejxudzy7vxyd.onion"
    },
    {
        "content": "3\u00a0weeks, 6\u00a0days",
        "description": "Holy Bible Aionian Edition\u00ae ~ The world's first Holy Bible untranslation! ~ English---Aionian-Bible ~ Table of Contents Description",
        "title": "Holy Bible Aionian Edition\u00ae ~ English---Aionian-Bible ~ Table of Contents Description",
        "url": "http://sy3tqe5tvukyk35kbqx4v3xjj5jxkrvrcdno4c4neg5kymz3zb5avzqd.onion"
    },
    {
        "content": "3\u00a0weeks, 6\u00a0days",
        "description": "Holy Bible Aionian Edition\u00ae ~ The world's first Holy Bible untranslation! ~ English---Catholic-Public-Domain ~ Table of Contents Description",
        "title": "Holy Bible Aionian Edition\u00ae ~ English---Catholic-Public-Domain ~ Table of Contents Description",
        "url": "http://sy3tqe5tvukyk35kbqx4v3xjj5jxkrvrcdno4c4neg5kymz3zb5avzqd.onion"
    },
    {
        "content": "4\u00a0weeks",
        "description": "Buy Bulk Drugs Quickly &             Discreetly.",
        "title": "Hosting in the onion sphere",
        "url": "http://hostingut6hqa6wvrix4b3s6kcser5w73tjiiuqqt6mevsrkvplqipid.onion"
    },
    {
        "content": "4\u00a0weeks",
        "description": "Anonymous Hosting, Comparison Table of Tor Onion Services, VPN with Remote Port Forwarding, PageKite and Anonymous Third Party Hosts",
        "title": "Hosting Location Hidden Services - Whonix",
        "url": "http://dds6qkxpeiqvogt4y2fd7vtsxq6pvokekb2h4la7jd4iwl4ljuawu5qd.onion"
    },
    {
        "content": "4\u00a0weeks",
        "description": "No description provided",
        "title": "How to Install, Configure, and Run V2Ray + WebSocket + TLS + CDN",
        "url": "http://gpp6nwvsps43b3mfacsh433uroo6uyjvvpr6tgj4jh4n5ngxt7rqbvid.onion"
    },
    {
        "content": "4\u00a0weeks",
        "description": "No description provided",
        "title": "hpkp Archives - BusKill",
        "url": "http://www.buskillvampfih2iucxhit3qp36i2zzql3u6pmkeafvlxs3tlmot5yad.onion"
    },
    {
        "content": "4\u00a0weeks",
        "description": "No description provided",
        "title": "https Archives - BusKill",
        "url": "http://www.buskillvampfih2iucxhit3qp36i2zzql3u6pmkeafvlxs3tlmot5yad.onion"
    },
    {
        "content": "3\u00a0weeks, 6\u00a0days",
        "description": "Online journal about autism, computing, economics, environmentalism, philosophy, privacy, society, and spirituality.",
        "title": "ICANNot Be Trusted",
        "url": "http://nick6gsepvtmkcpibpid6dqtqroxt62u6ab4ep65vxrenffruumj6jad.onion"
    },
    {
        "content": "3\u00a0weeks, 5\u00a0days",
        "description": "If we encounter an .onion domain in a reseed URL, automatically set the proxy to Tor's default if a proxy is not already configured. If the user...",
        "title": "If we encounter an .onion domain in a reseed URL, automatically set the proxy... (!46) \u00b7 Merge reque",
        "url": "http://47ggr2fijsircl3fetu64k5euw37yavfrezhag5o2imqy6vd62j6ucyd.onion"
    },
    {
        "content": "3\u00a0weeks, 6\u00a0days",
        "description": "No description provided",
        "title": "I installed Utopia so you don't have to - Archive - MayVaneDay Studios",
        "url": "http://sabladem4rxv5p34qcpz6sxitmftvmzmlzi4cjmmh5a3phcvdi3k2wad.onion"
    },
    {
        "content": "3\u00a0weeks, 6\u00a0days",
        "description": "No description provided",
        "title": "Improved ADOM Guidebook - Ice Queen Domain",
        "url": "http://sqtwtf2gx2up4nu32cx3qthvgvn3s22vh33h4arrty5kolsiir4k5hqd.onion"
    },
    {
        "content": "1\u00a0month, 4\u00a0weeks",
        "description": "Welcome to The Tor Project's Gitlab",
        "title": "Index \u00b7 Enterprise user \u00b7 User \u00b7 Help \u00b7 GitLab",
        "url": "http://eweiibe6tdjsdprb4px6rqrzzcsi22m4koia44kc5pcjr7nec2rlxyad.onion"
    },
    {
        "content": "3\u00a0weeks, 5\u00a0days",
        "description": "The I2P Gitlab",
        "title": "Index \u00b7 Pages \u00b7 Project \u00b7 User \u00b7 Help \u00b7 GitLab",
        "url": "http://47ggr2fijsircl3fetu64k5euw37yavfrezhag5o2imqy6vd62j6ucyd.onion"
    },
    {
        "content": "1\u00a0month, 3\u00a0weeks",
        "description": "No description provided",
        "title": "IndieAuth as a Persona Identity Provider",
        "url": "http://xfdug5vmfi6oh42fp6ahhrqdjcf7ysqat6fkp5dhvde4d7vlkqixrsad.onion"
    },
    {
        "content": "4\u00a0weeks",
        "description": "No description provided",
        "title": "Introduction to Qubes",
        "url": "http://kushal76uaid62oup5774umh654scnu5dwzh4u2534qxhcbi4wbab3ad.onion"
    },
    {
        "content": "4\u00a0weeks",
        "description": "No description provided",
        "title": "Iodine DNS Tunnel on Port 53",
        "url": "http://gpp6nwvsps43b3mfacsh433uroo6uyjvvpr6tgj4jh4n5ngxt7rqbvid.onion"
    },
    {
        "content": "3\u00a0weeks, 6\u00a0days",
        "description": "No description provided",
        "title": "It's insane, the things you can get simply by asking - Archive - MayVaneDay Studios",
        "url": "http://sabladem4rxv5p34qcpz6sxitmftvmzmlzi4cjmmh5a3phcvdi3k2wad.onion"
    },
    {
        "content": "3\u00a0weeks, 6\u00a0days",
        "description": "Online journal about autism, computing, economics, environmentalism, philosophy, privacy, society, and spirituality.",
        "title": "Journal Update 021",
        "url": "http://nick6gsepvtmkcpibpid6dqtqroxt62u6ab4ep65vxrenffruumj6jad.onion"
    },
    {
        "content": "3\u00a0weeks, 5\u00a0days",
        "description": "No description provided",
        "title": "Kaizushi's Little Onion Server - Site Coming Soon",
        "url": "http://yd3l2r7e5u5yrsawp45zbgvagxbywmigsn7jvinsozwhito5rov6taqd.onion"
    },
    {
        "content": "3\u00a0weeks, 5\u00a0days",
        "description": "No description provided",
        "title": "keys.openpgp.org",
        "url": "http://zkaan2xfbuxia2wpf7ofnkbz6r5zdbbvxbunvp5g2iebopbfc4iqmbad.onion"
    },
    {
        "content": "1\u00a0week, 1\u00a0day",
        "description": "KryptoPayPal :: PayPal Cashout Service",
        "title": "KryptoPayPal \u2022 PayPal Cashout Service",
        "url": "http://kptv3bqspwhe33ypttpblrbwmjt5la3xco6iuvzcfyldvksw2fc6pwyd.onion"
    },
    {
        "content": "4\u00a0weeks",
        "description": "FOSS and life. Kushal Das talks here.",
        "title": "Kushal Das",
        "url": "http://kushal76uaid62oup5774umh654scnu5dwzh4u2534qxhcbi4wbab3ad.onion"
    },
    {
        "content": "4\u00a0weeks",
        "description": "Kybernetiq, das erste deutschsprachige Magazin von Mudschahidin mit den Schwerpunkten Informationstechnologie, Kommunikation und Sicherheit.",
        "title": "KYBERNETIQ - MACH ETWAS, WAS BEI ALLAH WIRKLICH Z\u00c4HLT",
        "url": "http://kyberneukycfxugfsenx6f3ndxu7woufobarndbma7mdku2ywp7zq3ad.onion"
    },
    {
        "content": "4\u00a0weeks",
        "description": "Probleme mit der offiziellen Domain",
        "title": "KYBERNETIQ - Probleme mit der offiziellen Domain",
        "url": "http://kyberneukycfxugfsenx6f3ndxu7woufobarndbma7mdku2ywp7zq3ad.onion"
    },
    {
        "content": "4\u00a0weeks",
        "description": "Kybernetiq, das erste deutschsprachige Magazin von Mudschahidin mit den Schwerpunkten Informationstechnologie, Kommunikation und Sicherheit.",
        "title": "KYBERNETIQ - Tag Archiv",
        "url": "http://kyberneukycfxugfsenx6f3ndxu7woufobarndbma7mdku2ywp7zq3ad.onion"
    },
    {
        "content": "3\u00a0weeks, 6\u00a0days",
        "description": "No description provided",
        "title": "Latest Brave browser update fixes Tor .onion DNS Leak",
        "url": "http://rambleeysnwq5bpbefpycwkdvrxbhrs2e2te7prnrq4rravx7suak5qd.onion"
    },
    {
        "content": "4\u00a0weeks",
        "description": "Information about our list for Free Software licensing questions.",
        "title": "Legal FAQs - FSFE",
        "url": "http://fsfeorg3v5yaitpw5362njmkgvwm6z2qojrgol6edqyaqswlpliqrqid.onion"
    },
    {
        "content": "3\u00a0weeks, 6\u00a0days",
        "description": "Server Message Block (SMB), also known as Common Internet File System (CIFS), is a network protocol mainly used for providing shared access to files, printers, serial ports and miscellaneous communica",
        "title": "Let's hack some SMB",
        "url": "http://reycdxyc24gf7jrnwutzdn3smmweizedy7uojsa7ols6sflwu25ijoyd.onion"
    },
    {
        "content": "4\u00a0weeks",
        "description": "Join me on my journey preserving, repairing and enhancing retrogaming and retrocomputing hardware. Exploding things is just a part of the process!",
        "title": "Let\u2019s Encrypt Certbot Domain Listing Order \u2013 McRetro.net",
        "url": "http://mcretro4lov3ycyvikjdeer3dgl5wel5aer6xakj5mxa26a3qvrp22qd.onion"
    },
    {
        "content": "3\u00a0weeks, 6\u00a0days",
        "description": "No description provided",
        "title": "LibreNMS NGINX Debian 10",
        "url": "http://nihilhfjmj55gfbleupwl2ub7lvbhq4kkoioatiopahfqwkcnglsawyd.onion"
    },
    {
        "content": "4\u00a0weeks",
        "description": "No description provided",
        "title": "Linux Commands Cheat Sheet - PCWDLD",
        "url": "http://educatez5f7sveo73nutfv6vmrdxoltmgx3iedbidtatexoj376rqhid.onion"
    },
    {
        "content": "1\u00a0week, 1\u00a0day",
        "description": "Test your ability at spotting potential lookalike domains in real-time.",
        "title": "Lookalike Domain Names Test",
        "url": "http://jamie3vkiwibfiwucd6vxijskbhpjdyajmzeor4mc4i7yopvpo4p7cyd.onion"
    },
    {
        "content": "3\u00a0weeks, 6\u00a0days",
        "description": "Welcome to Paradise of Combo Lists! I am here to provide you with the best services for combo lists.",
        "title": "LuCYcl Store - Best Services For Combo Lists",
        "url": "http://pjnd7r7qiuntnwvzlv374etbuyi7a7qyges7r2i3m2iy7lajmlytlhqd.onion"
    },
    {
        "content": "4\u00a0weeks",
        "description": "hello??",
        "title": "Marty McGuire \u2022 Recent Posts - Marty McGuire",
        "url": "http://martymcgfuraocsgy2a25btl5srhifcdud6m4eiphz2mq6fafttwh7qd.onion"
    },
    {
        "content": "1\u00a0month, 3\u00a0weeks",
        "description": "Be crime do gay",
        "title": "Matrix is weird",
        "url": "http://lpoaj7z2zkajuhgnlltpeqh3zyq7wk2iyeggqaduhgxhyajtdt2j7wad.onion"
    },
    {
        "content": "4\u00a0weeks",
        "description": "No description provided",
        "title": "Migrating to anthes.is \u2014 anthesis",
        "url": "http://jentyxddh2rf47gd3e43kuebyn2xsv6h72gzh46oe4rxyovvm7xe5ead.onion"
    },
    {
        "content": "4\u00a0weeks",
        "description": "No description provided",
        "title": "NaiveProxy + Caddy 2",
        "url": "http://gpp6nwvsps43b3mfacsh433uroo6uyjvvpr6tgj4jh4n5ngxt7rqbvid.onion"
    },
    {
        "content": "4\u00a0weeks",
        "description": "No description provided",
        "title": "Network isolation using NetVMs and VPN in Qubes",
        "url": "http://kushal76uaid62oup5774umh654scnu5dwzh4u2534qxhcbi4wbab3ad.onion"
    },
    {
        "content": "4\u00a0weeks",
        "description": "Latest events about this server",
        "title": "News - \u300e\u6df7\u6c8c\u3068\u3057\u305f \u5fcd\u8005\u300f",
        "url": "http://chaoshhd35e5n6mezvffq2qeavasaxajvdxxme437ikdkw5b3irlenid.onion"
    },
    {
        "content": "3\u00a0weeks, 6\u00a0days",
        "description": "No description provided",
        "title": "Nginx HTTPS",
        "url": "http://nihilhfjmj55gfbleupwl2ub7lvbhq4kkoioatiopahfqwkcnglsawyd.onion"
    },
    {
        "content": "3\u00a0weeks, 6\u00a0days",
        "description": "No description provided",
        "title": "ni-chan",
        "url": "http://plnemls6yc5sxg6nqedescivpxoa5znpiu4pwrpsmtuknjzshyi5dmad.onion"
    },
    {
        "content": "1\u00a0month, 4\u00a0weeks",
        "description": "Anonymous privacy hosting, offshore hosting, uncensored hosting, shared hosting, VPS, virtual private servers, dedicated servers, VDS, virtual dedicated servers, VPN with instant and automatic delivery accepting Bitcoin, Monero, Litecoin, Ethereum, and other Altcoins",
        "title": "NiceVPS.net - Domains - Register domain, domain names, anonymous domain name, anonymous domains, off",
        "url": "http://nicevpsb7u3vqpo5zhyahmvfi5tihon4gnh676ucmzpcyxwodeztr4yd.onion"
    },
    {
        "content": "3\u00a0weeks, 6\u00a0days",
        "description": "No description provided",
        "title": "nihilist - Forest Writeup",
        "url": "http://nihilhfjmj55gfbleupwl2ub7lvbhq4kkoioatiopahfqwkcnglsawyd.onion"
    },
    {
        "content": "3\u00a0weeks, 6\u00a0days",
        "description": "No description provided",
        "title": "nihilist - Friendzone Writeup",
        "url": "http://nihilhfjmj55gfbleupwl2ub7lvbhq4kkoioatiopahfqwkcnglsawyd.onion"
    },
    {
        "content": "3\u00a0weeks, 6\u00a0days",
        "description": "No description provided",
        "title": "nihilist - Monteverde Writeup",
        "url": "http://nihilhfjmj55gfbleupwl2ub7lvbhq4kkoioatiopahfqwkcnglsawyd.onion"
    },
    {
        "content": "3\u00a0weeks, 6\u00a0days",
        "description": "No description provided",
        "title": "Njalla \u2014 .haus",
        "url": "http://njallalwgdliypxicms5dyte23vmdqcpsh4wromntl5gevdeprimlnad.onion"
    },
    {
        "content": "2\u00a0weeks, 5\u00a0days",
        "description": "No description provided",
        "title": "Njalla \u2014 Blog",
        "url": "http://njallalafimoej5i4eg7vlnqjvmb6zhdh27qxcatdn647jtwwwui3nad.onion"
    },
    {
        "content": "3\u00a0weeks, 6\u00a0days",
        "description": ">From: [redacted]@dhl[redacted] >To: abuse@[redacted] >Subject: dhlsucks.com > >We noticed your registration of the domain dhlsucks.com. Unless you have been authorized by DHL to register this domain, >your act violates our client&#39;s intellectual property rights and is aga\u2026",
        "title": "Njalla \u2014 DHL sucks",
        "url": "http://njallalafuehuazsodg4ghilydxhs7twe36nftokc3re4uiumpxs7xqd.onion"
    },
    {
        "content": "2\u00a0weeks, 5\u00a0days",
        "description": "No description provided",
        "title": "Njalla \u2014 Domains",
        "url": "http://njallalafimoej5i4eg7vlnqjvmb6zhdh27qxcatdn647jtwwwui3nad.onion"
    },
    {
        "content": "2\u00a0weeks, 5\u00a0days",
        "description": "No description provided",
        "title": "Njalla \u2014 FAQ",
        "url": "http://njallalafimoej5i4eg7vlnqjvmb6zhdh27qxcatdn647jtwwwui3nad.onion"
    },
    {
        "content": "3\u00a0weeks, 6\u00a0days",
        "description": "A lot of people are public about their usage of Njalla. We however find that it's their prerogative to decide if they want to acknowledge our relationship. We\u2019re like that secret partner that\u2019s ok with being a secret, maybe kept on the side or maybe just because real intimacy is the business o\u2026",
        "title": "Njalla \u2014 Hi, jack.",
        "url": "http://njallalafuehuazsodg4ghilydxhs7twe36nftokc3re4uiumpxs7xqd.onion"
    },
    {
        "content": "3\u00a0weeks, 6\u00a0days",
        "description": "FOR IMMACULATE RELEASE. Announcing the opening of NJAL.LA",
        "title": "Njalla \u2014 IMMACULATE RELEASE",
        "url": "http://njallalwgdliypxicms5dyte23vmdqcpsh4wromntl5gevdeprimlnad.onion"
    },
    {
        "content": "3\u00a0weeks, 6\u00a0days",
        "description": "No description provided",
        "title": "Njalla \u2014 Terms of service",
        "url": "http://njallalafuehuazsodg4ghilydxhs7twe36nftokc3re4uiumpxs7xqd.onion"
    },
    {
        "content": "3\u00a0weeks, 6\u00a0days",
        "description": "Njalla \u2014 Considered the worlds most notorious &quote;Privacy as a Service&quote; provider for domains, VPS' and VPNs.",
        "title": "Njalla \u2014 Worlds most notorious privacy provider for domains, VPS' and VPNs.",
        "url": "http://njallalwgdliypxicms5dyte23vmdqcpsh4wromntl5gevdeprimlnad.onion"
    },
    {
        "content": "4\u00a0weeks",
        "description": "No description provided",
        "title": "notify about domain migration - website_md - Source for www.anthes.is",
        "url": "http://jentyxddh2rf47gd3e43kuebyn2xsv6h72gzh46oe4rxyovvm7xe5ead.onion"
    },
    {
        "content": "4\u00a0weeks",
        "description": "Offshore dedicated servers, domains and web hosting with maximum efficiency and 24-hour support",
        "title": "Offshore Dedicated Servers, baremetal servers and domains - Impreza Host",
        "url": "http://portal.imprezareshna326gqgmbdzwmnad2wnjmeowh45bs2buxarh5qummjad.onion"
    },
    {
        "content": "4\u00a0weeks",
        "description": "No description provided",
        "title": "onion Archives - BusKill",
        "url": "http://www.buskillvampfih2iucxhit3qp36i2zzql3u6pmkeafvlxs3tlmot5yad.onion"
    },
    {
        "content": "1\u00a0month, 3\u00a0weeks",
        "description": "No description provided",
        "title": "onion domain - BUY TOR .ONION DOMAIN AND DARK WEB MARKETPLACE SCRIPTS",
        "url": "http://tordevfzeebs4nvzhpofkfywslbgmwlamonu4xfofcxzfpa4cschuiqd.onion"
    },
    {
        "content": "4\u00a0weeks",
        "description": "No description provided",
        "title": "onion WordPress Installer \u2013 BLACK MARKET \u2013 hacking Services, Drugs, Western Union Transfer, PayPal A",
        "url": "http://black37fsrox4nr3r4oorwnnvrobfjfih5sbcqf6khzkcxlrhfsex4id.onion"
    },
    {
        "content": "4\u00a0weeks",
        "description": "No description provided",
        "title": "OpenConnect",
        "url": "http://gpp6nwvsps43b3mfacsh433uroo6uyjvvpr6tgj4jh4n5ngxt7rqbvid.onion"
    },
    {
        "content": "1\u00a0month, 3\u00a0weeks",
        "description": "Abusing SecurityTrails domain suggestion API to find potentially related domains by keyword and brute force.",
        "title": "OSINT Tool to Abuse SecurityTrails Domain Suggestion API To Find Potentially Related Domains By Keyw",
        "url": "http://dreamshk3pkeizw2rfdxn73odxuido3rwevvt4sfl3ewc4frvcf5h4yd.onion"
    },
    {
        "content": "4\u00a0weeks",
        "description": "No description provided",
        "title": "other services \u2013 BLACK MARKET \u2013 hacking Services, Drugs, Western Union Transfer, PayPal Account, Cre",
        "url": "http://black37fsrox4nr3r4oorwnnvrobfjfih5sbcqf6khzkcxlrhfsex4id.onion"
    },
    {
        "content": "3\u00a0weeks, 6\u00a0days",
        "description": "Payoneer carding method  Published on: 1st Sept 2021  In this carding guide, you will learn how to Cash out cc with Payoneer - Payoneer Carding Tutorial, You don't need to have completed the previous tutorial to understand what's going on here, but if you're new to the carding ecosys\u2026",
        "title": "Payoneer Carding 2021 Tutorial -  nonvbv.info",
        "url": "http://op3xb7oc2szjk7pfwzqfpseu7a6jeo7uf4ig5cwwjhmfqelautiwknyd.onion"
    },
    {
        "content": "1\u00a0month, 3\u00a0weeks",
        "description": "No description provided",
        "title": "Persona Guiding Principles",
        "url": "http://xfdug5vmfi6oh42fp6ahhrqdjcf7ysqat6fkp5dhvde4d7vlkqixrsad.onion"
    },
    {
        "content": "4\u00a0weeks",
        "description": "No description provided",
        "title": "PoPETs Proceedings \u2014 Blocking-resistant communication through domain fronting",
        "url": "http://g7ee5otfyict57k24vjujuqzi6pd7iwvnsry2mt3svsgwzn6o6iynsad.onion"
    },
    {
        "content": "2\u00a0weeks, 5\u00a0days",
        "description": "No description provided",
        "title": "portfolio \u2013 U.S Intelligence Community 2.0",
        "url": "http://ddanatozv47wxowehimwkzukppplz3xmko2p7eeifle6gnbmdcqsqyad.onion"
    },
    {
        "content": "3\u00a0weeks, 6\u00a0days",
        "description": "FarsightAD is a PowerShell script that aim to help uncovering (eventual) persistence mechanisms deployed by a threat actor following an Active Directory",
        "title": "PowerShell Script That Aim To Help Uncovering (Eventual) Persistence Mechanisms Deployed By A Threat",
        "url": "http://u7pw75fv5lpll4adet6h6g32yayisfdcvmf5rjgb52glfysnci5gg6yd.onion"
    },
    {
        "content": "4\u00a0weeks",
        "description": "No description provided",
        "title": "privacy Archives - BusKill",
        "url": "http://www.buskillvampfih2iucxhit3qp36i2zzql3u6pmkeafvlxs3tlmot5yad.onion"
    },
    {
        "content": "1\u00a0month, 3\u00a0weeks",
        "description": "We offer anonymous server hosting solutions, featuring servers, domain registrations and dns parking. We do not require any personal information from you. Pay with Bitcoin and Monero.",
        "title": "Privacy friendly hosting solutions",
        "url": "http://mynymecyaiv7t55qiggp76rzqz35si5g7nzdh3yci4wiqbmlwqg7xeyd.onion"
    },
    {
        "content": "3\u00a0weeks, 5\u00a0days",
        "description": "Everything about Brand Indicators for Message Identification (BIMI) feels so half-baked. Lukewarm take: BIMI should mandate DMARC with DKIM and just ignore SPF.",
        "title": "Problems with BIMI - Seirdy",
        "url": "http://wgq3bd2kqoybhstp77i3wrzbfnsyd27wt34psaja4grqiezqircorkyd.onion"
    },
    {
        "content": "2\u00a0weeks, 5\u00a0days",
        "description": "No description provided",
        "title": "Profiling a Currently Active Domain Portfolio of Pay-Per-Install Rogue and Fraudulent Affiliate Netw",
        "url": "http://ddanatozv47wxowehimwkzukppplz3xmko2p7eeifle6gnbmdcqsqyad.onion"
    },
    {
        "content": "4\u00a0weeks",
        "description": "No description provided",
        "title": "Prosody Guide",
        "url": "http://arcani5qce7mhpqnemrmj2mv5dx2qjxnfzw5d3vzuvs5bqlzb65nkbyd.onion"
    },
    {
        "content": "3\u00a0weeks, 6\u00a0days",
        "description": "No description provided",
        "title": "Pseudo top-level domain - The Hidden Wiki",
        "url": "http://rk56xqf2fwp76cl4cwbarmsnn5nveqrurmvn7ek2yeqez52nq7awb2qd.onion"
    },
    {
        "content": "4\u00a0weeks",
        "description": "No description provided",
        "title": "Public Amazon S3 Buckets and the risk of data leakage",
        "url": "http://cumshitudpemjs4exlopowrjlxj4gw7z3tvelx3wxkbqyihxkulyvpid.onion"
    },
    {
        "content": "1\u00a0month, 4\u00a0weeks",
        "description": "No description provided",
        "title": "Public domain - Wikipedia",
        "url": "http://g6gr4dahewooeelw3h44qhqzr3x2jy475xm6rpve4m6hrsqe467lwxad.onion"
    },
    {
        "content": "3\u00a0weeks, 6\u00a0days",
        "description": "No description provided",
        "title": "Puellula - NewgonWiki",
        "url": "http://newgon7dchl3ltebxqpcatnbtkdhm3u4xelnzpwqm6ff4uewxcn54pyd.onion"
    },
    {
        "content": "3\u00a0weeks, 5\u00a0days",
        "description": "Group for Apps and Services on Exascale Research Infrastructure is a research, development, and teaching unit at FIDIT + MedRi.",
        "title": "Python -- usluge za vi\u0161ejezi\u010dnost - GASERI",
        "url": "http://vcwkbqby652dtqgbtbtr6ouvs6fu5abx5z45dmlug6dl55d6zcadsuqd.onion"
    },
    {
        "content": "4\u00a0weeks",
        "description": "No description provided",
        "title": "Qubes OS part 2",
        "url": "http://kushal76uaid62oup5774umh654scnu5dwzh4u2534qxhcbi4wbab3ad.onion"
    },
    {
        "content": "4\u00a0weeks",
        "description": "No description provided",
        "title": "Quickly Set Up Trojan-GFW",
        "url": "http://gpp6nwvsps43b3mfacsh433uroo6uyjvvpr6tgj4jh4n5ngxt7rqbvid.onion"
    },
    {
        "content": "4\u00a0weeks",
        "description": "No description provided",
        "title": "Quickly Set Up Trojan-Go",
        "url": "http://gpp6nwvsps43b3mfacsh433uroo6uyjvvpr6tgj4jh4n5ngxt7rqbvid.onion"
    },
    {
        "content": "4\u00a0weeks",
        "description": "Be crime do gay",
        "title": "Recent changes to services",
        "url": "http://lpoaj7zvyrnceulk7tgqppz6pdf3r3panu6t6lh5zeykmojvdmzem5ad.onion"
    },
    {
        "content": "1\u00a0month, 4\u00a0weeks",
        "description": "Welcome to The Tor Project's Gitlab",
        "title": "Requirements \u00b7 Autodevops \u00b7 Topics \u00b7 Help \u00b7 GitLab",
        "url": "http://eweiibe6tdjsdprb4px6rqrzzcsi22m4koia44kc5pcjr7nec2rlxyad.onion"
    },
    {
        "content": "1\u00a0week, 1\u00a0day",
        "description": "Using Certificate Authority Authorisation (CAA) to restrict the Certificate Authorities that are permitted to issue certificates for your domain.",
        "title": "Restricting Who Can Issue Certificates for Your Domain with CAA",
        "url": "http://jamie3vkiwibfiwucd6vxijskbhpjdyajmzeor4mc4i7yopvpo4p7cyd.onion"
    },
    {
        "content": "4\u00a0weeks",
        "description": "All rituals restricted. All rites reserved.",
        "title": "Running Wiki.js on Fly.io with Litestream backups",
        "url": "http://mgv3s6mkbisnggxz5xg3f75vkch67qmj5fkw5yaaazztaqofmgplddad.onion"
    },
    {
        "content": "4\u00a0weeks",
        "description": "No description provided",
        "title": "Scribe FAQ",
        "url": "http://3xejtix5tkneqclwbcuqi2mysi3bqp6qv2b3jwp466itjzjjptiwhdqd.onion"
    },
    {
        "content": "2\u00a0weeks, 5\u00a0days",
        "description": "A fast simple no javascript tor search engine. Explore tor hidden services on darkweb",
        "title": "Search results for if    - Torgol",
        "url": "http://torgolnpeouim56dykfob6jh5r2ps2j73enc42s2um4ufob3ny4fcdyd.onion"
    },
    {
        "content": "4\u00a0weeks",
        "description": "No description provided",
        "title": "secure_browsing [\ud83d\udd12 Cybersecurity for lawyers]",
        "url": "http://h7isucmawckzflxhipflydxvxpaytk5fozfk5immffg66rhboc74yxyd.onion"
    },
    {
        "content": "3\u00a0weeks, 6\u00a0days",
        "description": "CRYPTOMIXER.IO - \u0410\u041d\u041e\u041d\u0418\u041c\u041d\u042b\u0419 \u041b\u0423\u0427\u0428\u0418\u0419 \u041c\u0418\u041a\u0421\u0415\u0420 \u0411\u0418\u0422\u041a\u041e\u0418\u041d\u041e\u0412 - CRYPTO MIXER",
        "title": "Sell domain name for bitcoin - ANONYMOUS BEST BITCOIN MIXER - CRYPTO MIXER",
        "url": "http://s4evplhm4moys3eyrmeetmshntguym6tuoxokhxp5zlus5s4knjv5lid.onion"
    },
    {
        "content": "3\u00a0weeks, 5\u00a0days",
        "description": "Sell domain names for bitcoin - With our service blender.io you will be able to conduct completely anonymous transactions without using VPN. Our bitcoin blender mixes your bitcoins anonymously.",
        "title": "Sell domain names for bitcoin - BLENDER BITCOIN BLENDER, BTC BLENDER BTC",
        "url": "http://yu5y7byjliwsfhizyfspvj264c3isurizoj5dojv2zq6yn4au5rbfyyd.onion"
    },
    {
        "content": "3\u00a0weeks, 6\u00a0days",
        "description": "It is good if your server can talk to you. Maybe not literally, but it\u2019s good if it can send you emails with logs or issues. It\u2019s also nice to allow your website script located on server to send some",
        "title": "Send emails by local applications only",
        "url": "http://reycdxyciow233cvfrssa2bp4idzqa36i2dgz2jxpxde6cr4cvhzhzad.onion"
    },
    {
        "content": "4\u00a0weeks",
        "description": "Dear friends, I hope this message finds you well. I would like to inform everyone that the blog experienced some instability yesterday due to an attack on my home server from the I2P network for a few hours. In summary, after examining the logs, it became apparent that thousands of requests per min\u2026",
        "title": "Server Instability Announcement \u00b7 Elder Rocker",
        "url": "http://acnnwjkiuoqhexhtlhjr7plkbe7wfnkmjdkxw7uziuyymujkmyem6bid.onion"
    },
    {
        "content": "3\u00a0weeks, 5\u00a0days",
        "description": "No description provided",
        "title": "servers.conf",
        "url": "http://vzoc4aylgsqwexe6okjbz2ix5atgdv5xyibnkcekmtg4u23syz6a7rid.onion"
    },
    {
        "content": "3\u00a0weeks, 6\u00a0days",
        "description": "FlokiNET provides Secure, Stable and Anonymous Webhosting, Virtual Servers, Colocation, Dedicated Servers, DDoS Protection & more in Iceland Finland Netherlands and Romania",
        "title": "Shared Hosting - FlokiNET",
        "url": "http://vf7vsrexwb7e4j65idp4hq4eqlvjiwrnvi3jnb4st7oteer5tzgvhaqd.onion"
    },
    {
        "content": "1\u00a0week, 4\u00a0days",
        "description": "No description provided",
        "title": "Shifting To An Anonymous Persona Setup",
        "url": "http://nihilhfjmj55gfbleupwl2ub7lvbhq4kkoioatiopahfqwkcnglsawyd.onion"
    },
    {
        "content": "3\u00a0weeks, 5\u00a0days",
        "description": "No description provided",
        "title": "Shopping Cart - FlokiNET",
        "url": "http://m5ddnpm3ukjrgoaa3dxatuxuw5bgtn3ikjsx2d7yy4v57pvtwipzccid.onion"
    },
    {
        "content": "3\u00a0weeks, 6\u00a0days",
        "description": "No description provided",
        "title": "Shopping Cart - Mynymbox",
        "url": "http://mynymefqtjhkxg67sj5orcsu75ofhvnyk7tpuowfe4jyhfvqsfsbhzyd.onion"
    },
    {
        "content": "3\u00a0weeks, 6\u00a0days",
        "description": "No description provided",
        "title": "Siteground sign up",
        "url": "http://rtdxrpt3wx3sk7mkp2l2ku7mrvrrgzzpvff7ik76ggss6by434fd6vid.onion"
    },
    {
        "content": "3\u00a0weeks, 6\u00a0days",
        "description": "Online journal about autism, computing, economics, environmentalism, philosophy, privacy, society, and spirituality.",
        "title": "Site Update 011",
        "url": "http://nick6gsepvtmkcpibpid6dqtqroxt62u6ab4ep65vxrenffruumj6jad.onion"
    },
    {
        "content": "4\u00a0weeks",
        "description": "10 IP SMTPs for sale, every SMTP you buy is a spam tool that sends inbox to all.Inbox to all Smtps are verified before delivery with our smtp",
        "title": "SMTP Spam - Dark Fox Market - Hacking Service",
        "url": "http://darkfox7kukhe3b2ufsvuknskyhzdjc7a724mh4zrkipeg7pkaikm6yd.onion"
    },
    {
        "content": "3\u00a0weeks, 6\u00a0days",
        "description": "A few years ago, taking over a subdomain was one of the easiest way to earn, several hundred dollars (sometimes thousands). It was a good salary for a beginner bounty hunter. Today, companies are more",
        "title": "Subdomain takeover",
        "url": "http://reycdxyc24gf7jrnwutzdn3smmweizedy7uojsa7ols6sflwu25ijoyd.onion"
    },
    {
        "content": "4\u00a0weeks",
        "description": "SuperBay: Switching to a New V3 Onion Domain on the Dark Web. Anonymous file sharing on the darkweb | Anonymous upload",
        "title": "SuperBay - Hidden Wiki",
        "url": "http://darkwebp7lyr44rpgqdtevalty2pk5oqmc6m2cnicnix7itelt3lp3id.onion"
    },
    {
        "content": "3\u00a0weeks, 6\u00a0days",
        "description": "No description provided",
        "title": "SuperBay \u2013 Hidden Wiki",
        "url": "http://oq2h5qzmhyu4arveocoa2m2h3musxqjr7x3lo7xm2v4f6xg77vzeu5yd.onion"
    },
    {
        "content": "3\u00a0weeks, 6\u00a0days",
        "description": "No description provided",
        "title": "S Y N T H E S I S -   Balkan Illusions by Sasha Papovic",
        "url": "http://tails6l7b4ilavjr7hckzin7cspswc3cniwll4atlmbiwaccwomtzeyd.onion"
    },
    {
        "content": "3\u00a0weeks, 6\u00a0days",
        "description": "Ramblings from a random GNU/Linux user, sysadmin, and professional multi-instrumentalist",
        "title": "Tags",
        "url": "http://nixnet54icmeh25qsmcsereuoareofzevjqjnw3kki6oxxey3jonwwyd.onion"
    },
    {
        "content": "1\u00a0week, 4\u00a0days",
        "description": "No description provided",
        "title": "Tails - License and source code distribution",
        "url": "http://tzoz3bensgxyzs7da7lpgsn3a74h7hlbm4wa6ytq2tg6ktd57w22vqqd.onion"
    },
    {
        "content": "3\u00a0weeks, 6\u00a0days",
        "description": "Personal Privacy and Security Consultant and Blogger. I help people blend in almost too well.",
        "title": "Technical Details \u00b7 Offensive Privacy",
        "url": "http://offprivqqdxfmssktx3y5h3miqvceq6yy37s5sxkhz4mojvsz74ohqid.onion"
    },
    {
        "content": "1\u00a0week, 1\u00a0day",
        "description": "Creating a JavaScript app to test how good you are at identifying potential lookalike domain names.",
        "title": "Testing Your Ability at Spotting Lookalike Domain Names",
        "url": "http://jamie3vkiwibfiwucd6vxijskbhpjdyajmzeor4mc4i7yopvpo4p7cyd.onion"
    },
    {
        "content": "4\u00a0weeks",
        "description": "No description provided",
        "title": "The Hidden Wiki",
        "url": "http://iyptqjjx5gtzukc2gtgywqq4johsjdtrudjdjrjnsn7ftqnjwdoaoyad.onion"
    },
    {
        "content": "1\u00a0month, 1\u00a0week",
        "description": "THE X WAVE MARKET - CyberSec101x Domain - Highly Secure ProtonMail E-mail Account - 3 High Speed VPN Connections 1 Year For sale at the most secured darknet marketplace. Your secure marketplace for drugs Cocaine, Ecstasy, LSD, Meth, cannabis, buy, marijuana, hashish, kush, Seeds Cannabis,Drugs Stor\u2026",
        "title": "THE X WAVE MARKET - CyberSec101x Domain - Highly Secure ProtonMail E-mail Account - 3 High Speed VPN",
        "url": "http://torchs64fx2yit6evmkrqelfddowhk2jpkhzlu7u5fk5n4wmayd3qnyd.onion"
    },
    {
        "content": "3\u00a0weeks, 6\u00a0days",
        "description": "I had completely forgotten about this topic. I remembered that I was interested in it in the past, but when the topic of TLS certificates for onion domains came up, it was only available from DigiCert",
        "title": "TLS Certificate for Onion domain",
        "url": "http://reycdxyciow233cvfrssa2bp4idzqa36i2dgz2jxpxde6cr4cvhzhzad.onion"
    },
    {
        "content": "3\u00a0weeks, 5\u00a0days",
        "description": "Trusted resource of verified darknet links. Our mission is to tracking uptime and service providers quality.",
        "title": "Tor.Watch - Verified Darknet Links",
        "url": "http://xq5hcm32cm4tyl3pi5r6yytmgevgtbj36d3wz2rabyubm26xcr5svvad.onion"
    },
    {
        "content": "1\u00a0month, 3\u00a0weeks",
        "description": "No description provided",
        "title": "tor domain - BUY TOR .ONION DOMAIN AND DARK WEB MARKETPLACE SCRIPTS",
        "url": "http://tordevfzeebs4nvzhpofkfywslbgmwlamonu4xfofcxzfpa4cschuiqd.onion"
    },
    {
        "content": "3\u00a0weeks, 6\u00a0days",
        "description": "No description provided",
        "title": "tor domain - Hire expert freelancers for any Dark web job, Online Millions of people use darkweb dev",
        "url": "http://trust3nercpefmktnhyp6hqpuz3ws3v7ynhuxynbjyaghyu72xfeafad.onion"
    },
    {
        "content": "1\u00a0month, 4\u00a0weeks",
        "description": "No description provided",
        "title": "tosdr.txt - A new way to crawl your service -- Terms of Service; Didn't Read",
        "url": "http://6tc72lnilgt4dn2u6qk44vfns2qca552smajbilfcl6zs7ezf7emhbad.onion"
    },
    {
        "content": "4\u00a0weeks",
        "description": "No description provided",
        "title": "Tracking my phone's silent connections",
        "url": "http://kushal76uaid62oup5774umh654scnu5dwzh4u2534qxhcbi4wbab3ad.onion"
    },
    {
        "content": "3\u00a0weeks, 6\u00a0days",
        "description": "less_retarded_wiki - LRS wiki :)",
        "title": "Update \u00b7 b531bd8542 - less_retarded_wiki - basedwa.re",
        "url": "http://pmo2bva2xhlxydq7zfswb6v4x4e32p3mj446tblj3hfi2rygh3lraqyd.onion"
    },
    {
        "content": "4\u00a0weeks",
        "description": "No description provided",
        "title": "US authorities seized hacking site Breach Forums \u2013 DarkNet",
        "url": "http://darknet47w5otuw7koxrqgasuljjh6dhz7dw5iapmsekhjqbwipfpsad.onion"
    },
    {
        "content": "1\u00a0month, 3\u00a0weeks",
        "description": "No description provided",
        "title": "v2 onion services deprecation, defending dissent, & domain shadowing",
        "url": "http://a4ygisnerpgtc5ayerl22pll6cls3oyj54qgpm7qrmb66xrxts6y3lyd.onion"
    },
    {
        "content": "4\u00a0weeks",
        "description": "No description provided",
        "title": "v2 onion services deprecation, improvements to Tor Browser, LGBTQIA+ rights & internet freedom",
        "url": "http://a4ygisnerpgtc5ayerl22pll6cls3oyj54qgpm7qrmb66xrxts6y3lyd.onion"
    },
    {
        "content": "1\u00a0month, 3\u00a0weeks",
        "description": "No description provided",
        "title": "v3 domain - BUY TOR .ONION DOMAIN AND DARK WEB MARKETPLACE SCRIPTS",
        "url": "http://tordevfzeebs4nvzhpofkfywslbgmwlamonu4xfofcxzfpa4cschuiqd.onion"
    },
    {
        "content": "4\u00a0weeks",
        "description": "No description provided",
        "title": "Validating DNS name against X.509 subject name",
        "url": "http://l3g7hlm7xkzxcqecf3lm3ziba36ntgpm7lweocq47kcodtffcableoad.onion"
    },
    {
        "content": "3\u00a0weeks, 5\u00a0days",
        "description": "No description provided",
        "title": "Vilebin",
        "url": "http://vilebrb3higienbfbd7xad5qwpvoyc7fwfrn3dp2htzoisiqaaz7rvid.onion"
    },
    {
        "content": "3\u00a0weeks, 6\u00a0days",
        "description": "Group for Apps and Services on Exascale Research Infrastructure is a research, development, and teaching unit at FIDIT + MedRi.",
        "title": "Virtualizacija kori\u0161tenjem libvirta - GASERI",
        "url": "http://vcwkbqby652dtqgbtbtr6ouvs6fu5abx5z45dmlug6dl55d6zcadsuqd.onion"
    },
    {
        "content": "4\u00a0weeks",
        "description": "No description provided",
        "title": "VLESS with Wulabing XRay Script",
        "url": "http://gpp6nwvsps43b3mfacsh433uroo6uyjvvpr6tgj4jh4n5ngxt7rqbvid.onion"
    },
    {
        "content": "3\u00a0weeks, 6\u00a0days",
        "description": "FlokiNET provides Secure, Stable and Anonymous Webhosting, Virtual Servers, Colocation, Dedicated Servers, DDoS Protection & more in Iceland Finland Netherlands and Romania",
        "title": "VPS - FlokiNET",
        "url": "http://vf7vsrexwb7e4j65idp4hq4eqlvjiwrnvi3jnb4st7oteer5tzgvhaqd.onion"
    },
    {
        "content": "4\u00a0weeks",
        "description": "No description provided",
        "title": "whonix Archives - BusKill",
        "url": "http://www.buskillvampfih2iucxhit3qp36i2zzql3u6pmkeafvlxs3tlmot5yad.onion"
    },
    {
        "content": "1\u00a0week, 4\u00a0days",
        "description": "No description provided",
        "title": "whonixqemuvms Setup",
        "url": "http://nihilhfjmj55gfbleupwl2ub7lvbhq4kkoioatiopahfqwkcnglsawyd.onion"
    },
    {
        "content": "3\u00a0weeks, 6\u00a0days",
        "description": "No description provided",
        "title": "Wix website hosting",
        "url": "http://rtdxrpt3wx3sk7mkp2l2ku7mrvrrgzzpvff7ik76ggss6by434fd6vid.onion"
    },
    {
        "content": "3\u00a0weeks, 5\u00a0days",
        "description": "Build your publication on the open web.",
        "title": "Write.as for Publications",
        "url": "http://writeasw4b635r4o3vec6mu45s47ohfyro5vayzx2zjwod4pjswyovyd.onion"
    },
    {
        "content": "4\u00a0weeks",
        "description": "No description provided",
        "title": "x509 Archives - BusKill",
        "url": "http://www.buskillvampfih2iucxhit3qp36i2zzql3u6pmkeafvlxs3tlmot5yad.onion"
    },
    {
        "content": "1\u00a0week, 4\u00a0days",
        "description": "No description provided",
        "title": "XMPP server (Gajim, OMEO encryption, ejabberd .onion setup)",
        "url": "http://nihilhfjmj55gfbleupwl2ub7lvbhq4kkoioatiopahfqwkcnglsawyd.onion"
    },
    {
        "content": "4\u00a0weeks",
        "description": "No description provided",
        "title": "Xray with VLESS and XTLS using ProxySU and Qv2ray",
        "url": "http://gpp6nwvsps43b3mfacsh433uroo6uyjvvpr6tgj4jh4n5ngxt7rqbvid.onion"
    },
    {
        "content": "3\u00a0weeks, 5\u00a0days",
        "description": "YTS YIFY Official Status site.",
        "title": "YTS YIFY Official Status site",
        "url": "http://ytsyifyupcmxftncrnqd4bmwxvhlibhdat74w6xnmn33njxts4eeaiqd.onion"
    },
    {
        "content": "1\u00a0month, 4\u00a0weeks",
        "description": "Hi! This is my status report for contract work done in March 2024.  # Snowflake development  The major updates to Snowflake I worked on this month were reviewing an deploying some SQS rendezvous fixes and improvements, a&hellip;",
        "title": "[tor-project] cohosh's monthly status report, March 2024 - tor-project - Tor Project Forum",
        "url": "http://v236xhqtyullodhf26szyjepvkbv6iitrhjgrqj4avaoukebkk6n6syd.onion"
    },
    {
        "content": "4\u00a0weeks",
        "description": "Encontre la forma definitiva de inyectar las cookies si inspeccionamos bien el archivo cookies.txt nos daremos ... sitio Bom Proveito!! <[:{D-G<",
        "title": "[Tutorial Definitivo] Inyeccion de cookies - Deep Answers",
        "url": "http://deeptyscjff323hetai3kgv7qaogtzt5scwgmzmiz7u264exulyn5eid.onion"
    },
    {
        "content": "2\u00a0weeks, 5\u00a0days",
        "description": "No description provided",
        "title": "\u2013 \u2013 U.S Intelligence Community 2.0",
        "url": "http://ddanatozv47wxowehimwkzukppplz3xmko2p7eeifle6gnbmdcqsqyad.onion"
    },
    {
        "content": "1\u00a0week, 4\u00a0days",
        "description": "",
        "title": "\u2709 disposable e-mail",
        "url": "http://csmail3thcskmzvjicww3qdkvrhb6pb5s7zjqtb3gdst6guby2stsiqd.onion"
    }
]